idr_torch/__init__.py
idr_torch/__init__.pyi
idr_torch/config.py
idr_torch/interface.py
idr_torch/notebook.py
idr_torch/utils.py
idr_torch/api/__init__.py
idr_torch/api/base.py
idr_torch/api/default.py
idr_torch/api/slurm.py
idr_torch/api/torchelastic.py
idr_torch/api/modifiers/__init__.py
idr_torch/api/modifiers/auto_master_addr_port.py
idr_torch/api/modifiers/decorate_methods.py
idr_torch/api/modifiers/undistributed_warning.py
idr_torch-2.5.0.dist-info/METADATA
idr_torch-2.5.0.dist-info/WHEEL
idr_torch-2.5.0.dist-info/top_level.txt
idr_torch-2.5.0.dist-info/RECORD
