Metadata-Version: 2.4
Name: idr_torch
Version: 2.5.0
Summary: Distribution initialization util tool
Author-email: Nathan Cassereau <nathan@cassereau.fr>
License: MIT
Project-URL: Homepage, https://github.com/ncassereau/idr_torch
Project-URL: Source, https://github.com/ncassereau/idr_torch
Classifier: Development Status :: 5 - Production/Stable
Classifier: License :: OSI Approved :: MIT License
Classifier: Programming Language :: Python :: 3
Classifier: Programming Language :: Python :: 3.8
Classifier: Programming Language :: Python :: 3.9
Classifier: Programming Language :: Python :: 3.10
Classifier: Programming Language :: Python :: 3.11
Classifier: Programming Language :: Python :: 3.12
Classifier: Programming Language :: Python :: 3 :: Only
Requires-Python: >=3.8
Provides-Extra: notebook
Requires-Dist: ipyparallel; extra == "notebook"
Provides-Extra: dev
Requires-Dist: ruff>=0.1.0; extra == "dev"
Requires-Dist: torch; extra == "dev"
Requires-Dist: python-hostlist; extra == "dev"
Requires-Dist: ipyparallel; extra == "dev"
